drillpy/__init__.py
drillpy/_drillpy.py
drillpy-0.2.0.dist-info/DESCRIPTION.rst
drillpy-0.2.0.dist-info/METADATA
drillpy-0.2.0.dist-info/RECORD
drillpy-0.2.0.dist-info/WHEEL
drillpy-0.2.0.dist-info/metadata.json
drillpy-0.2.0.dist-info/top_level.txt
