Metadata-Version: 2.0
Name: drillpy
Version: 0.2.0
Summary: Python wrapper for Apache Drill's REST API
Home-page: https://bitbucket.org/julioasoto/drillpy
Author: Julio Antonio Soto
Author-email: julio@esbet.es
License: MIT
Keywords: drill nosql api
Platform: UNKNOWN
Classifier: Development Status :: 3 - Alpha
Classifier: Environment :: Console
Classifier: Intended Audience :: Developers
Classifier: License :: OSI Approved :: MIT License
Classifier: Programming Language :: Python :: 2
Classifier: Programming Language :: Python :: 2.7
Classifier: Programming Language :: Python :: 3
Classifier: Programming Language :: Python :: 3.2
Classifier: Programming Language :: Python :: 3.3
Classifier: Programming Language :: Python :: 3.4
Classifier: Programming Language :: Python :: 3.5
Requires-Dist: numpy
Requires-Dist: pandas
Requires-Dist: requests
